datus_clickzetta/__init__.py
datus_clickzetta/config.py
datus_clickzetta/connector.py
datus_clickzetta-0.1.1.dist-info/METADATA
datus_clickzetta-0.1.1.dist-info/WHEEL
datus_clickzetta-0.1.1.dist-info/entry_points.txt
datus_clickzetta-0.1.1.dist-info/RECORD
