Metadata-Version: 2.4
Name: datus-clickzetta
Version: 0.1.1
Summary: ClickZetta database adapter for Datus
Project-URL: Homepage, https://github.com/Datus-ai/datus-db-adapters
Project-URL: Repository, https://github.com/Datus-ai/datus-db-adapters
Project-URL: Issues, https://github.com/Datus-ai/datus-db-adapters/issues
Author-email: DatusAI <support@datus.ai>
License: Apache-2.0
Keywords: adapter,clickzetta,database,datus,lakehouse
Classifier: Development Status :: 4 - Beta
Classifier: Intended Audience :: Developers
Classifier: License :: OSI Approved :: Apache Software License
Classifier: Programming Language :: Python :: 3
Classifier: Programming Language :: Python :: 3.12
Requires-Python: >=3.12
Requires-Dist: clickzetta-connector-python
Requires-Dist: clickzetta-zettapark-python
Requires-Dist: datus-agent>=0.2.1
Requires-Dist: pandas>=2.0.0
Requires-Dist: pyarrow>=10.0.0
Requires-Dist: pydantic>=2.0.0
